mcp_shell/__init__.py
mcp_shell/main.py
mcp_shell-0.0.1.dist-info/LICENSE
mcp_shell-0.0.1.dist-info/METADATA
mcp_shell-0.0.1.dist-info/WHEEL
mcp_shell-0.0.1.dist-info/top_level.txt
mcp_shell-0.0.1.dist-info/RECORD
